CHANGES.rst
COPYING
MANIFEST.in
README.rst
setup.py
example/CHANGES.rst
example/requirements.txt
example/setup.cfg
example/setup.py
example/example/__init__.py
example/example/test_all.py
pytest_bwrap/__init__.py
pytest_bwrap/_bwrap.py
pytest_bwrap/_host.py
pytest_bwrap/decorators.py
pytest_bwrap.egg-info/PKG-INFO
pytest_bwrap.egg-info/SOURCES.txt
pytest_bwrap.egg-info/dependency_links.txt
pytest_bwrap.egg-info/entry_points.txt
pytest_bwrap.egg-info/not-zip-safe
pytest_bwrap.egg-info/requires.txt
pytest_bwrap.egg-info/top_level.txt