Metadata-Version: 2.1
Name: pytest-bwrap
Version: 0.1.1
Summary: Run your tests in Bubblewrap sandboxes
Home-page: https://framagit.org/bochecha/pytest-bwrap/
Author: Mathieu Bridon
Author-email: bochecha@daitauha.fr
Classifier: Development Status :: 3 - Alpha
Classifier: Environment :: Plugins
Classifier: Framework :: Pytest
Classifier: Intended Audience :: Developers
Classifier: License :: OSI Approved :: GNU Lesser General Public License v3 or later (LGPLv3+)
Classifier: Programming Language :: Python :: 3 :: Only
Classifier: Topic :: Software Development :: Testing
License-File: COPYING
